{
  "name": "Kitchen Sink (Medium)",
  "description": "Everything! Platforms, bars, hazards - 20P/25B, 27 at max height",
  "obstacles": [
    {
      "bar_type": "bar-5-0",
      "gap_type": "gap-2.0"
    },
    {
      "bar_type": "bar-3-1-4",
      "gap_type": "gap-2.0"
    },
    {
      "bar_type": "bar-5-4",
      "gap_type": "gap-2.0"
    },
    {
      "bar_type": "bar-3-4-6",
      "gap_type": "gap-2.0"
    },
    {
      "bar_type": "bar-2-4",
      "gap_type": "gap-2.0"
    },
    {
      "bar_type": "bar-3-3-6",
      "gap_type": "gap-2.0-laser"
    },
    {
      "bar_type": "bar-4-3",
      "gap_type": "gap-2.0"
    },
    {
      "bar_type": "bar-2-3-5",
      "gap_type": "gap-2.25"
    },
    {
      "bar_type": "bar-8-3",
      "gap_type": "gap-2.25"
    },
    {
      "bar_type": "bar-6-4",
      "gap_type": "gap-2.25"
    },
    {
      "bar_type": "bar-3-4-6",
      "gap_type": "gap-2.0"
    },
    {
      "bar_type": "bar-4-3-5",
      "gap_type": "gap-2.0"
    },
    {
      "bar_type": "bar-3-4",
      "gap_type": "gap-2.0"
    },
    {
      "bar_type": "bar-9-4",
      "gap_type": "gap-2.0"
    },
    {
      "bar_type": "bar-4-4",
      "gap_type": "gap-1.75-saw"
    },
    {
      "bar_type": "bar-5-4",
      "gap_type": "gap-2.0"
    },
    {
      "bar_type": "bar-4-4-7",
      "gap_type": "gap-2.0"
    },
    {
      "bar_type": "bar-2-3-6",
      "gap_type": "gap-2.25"
    },
    {
      "bar_type": "bar-9-4-6",
      "gap_type": "gap-2.0"
    },
    {
      "bar_type": "bar-3-3-6",
      "gap_type": "gap-2.25"
    },
    {
      "bar_type": "bar-4-4",
      "gap_type": "gap-2.0"
    },
    {
      "bar_type": "bar-4-3",
      "gap_type": "gap-2.0-electric"
    },
    {
      "bar_type": "bar-3-3",
      "gap_type": "gap-2.0"
    },
    {
      "bar_type": "bar-9-3",
      "gap_type": "gap-1.75"
    },
    {
      "bar_type": "bar-6-4-6",
      "gap_type": "gap-1.75"
    },
    {
      "bar_type": "bar-4-4",
      "gap_type": "gap-2.0"
    },
    {
      "bar_type": "bar-6-4-7",
      "gap_type": "gap-2.25"
    },
    {
      "bar_type": "bar-4-4",
      "gap_type": "gap-1.75"
    },
    {
      "bar_type": "bar-6-3",
      "gap_type": "gap-2.25"
    },
    {
      "bar_type": "bar-3-4-6",
      "gap_type": "gap-1.75"
    },
    {
      "bar_type": "bar-5-4",
      "gap_type": "gap-2.0-electric"
    },
    {
      "bar_type": "bar-5-4",
      "gap_type": "gap-2.25-lava"
    },
    {
      "bar_type": "bar-5-4",
      "gap_type": "gap-2.0-lava"
    },
    {
      "bar_type": "bar-8-4",
      "gap_type": "gap-2.0"
    },
    {
      "bar_type": "bar-4-3",
      "gap_type": "gap-2.25-electric"
    },
    {
      "bar_type": "bar-3-3-6",
      "gap_type": "gap-2.0"
    },
    {
      "bar_type": "bar-4-3",
      "gap_type": "gap-2.0"
    },
    {
      "bar_type": "bar-5-2-4",
      "gap_type": "gap-2.25"
    },
    {
      "bar_type": "bar-5-4-7",
      "gap_type": "gap-2.0"
    },
    {
      "bar_type": "bar-6-4",
      "gap_type": "gap-2.0-lava"
    },
    {
      "bar_type": "bar-6-4-7",
      "gap_type": "gap-2.0"
    },
    {
      "bar_type": "bar-3-4",
      "gap_type": "gap-2.25"
    },
    {
      "bar_type": "bar-8-4-6",
      "gap_type": "gap-2.0"
    },
    {
      "bar_type": "bar-4-4-6",
      "gap_type": "gap-2.0"
    },
    {
      "bar_type": "bar-4-3-5",
      "gap_type": "gap-2.0"
    },
    {
      "bar_type": "bar-8-2",
      "gap_type": "gap-2.0"
    }
  ],
  "metadata": {
    "type": "mixed",
    "length": 46,
    "rhythm": "Ultimate variety"
  }
}